odoo/addons/account_move_line_landed_cost_info/README.rst
odoo/addons/account_move_line_landed_cost_info/__init__.py
odoo/addons/account_move_line_landed_cost_info/__manifest__.py
odoo/addons/account_move_line_landed_cost_info/hooks.py
odoo/addons/account_move_line_landed_cost_info/i18n/account_move_line_landed_cost_info.pot
odoo/addons/account_move_line_landed_cost_info/i18n/it.po
odoo/addons/account_move_line_landed_cost_info/models/__init__.py
odoo/addons/account_move_line_landed_cost_info/models/account_move.py
odoo/addons/account_move_line_landed_cost_info/models/stock_valuation_adjustment_lines.py
odoo/addons/account_move_line_landed_cost_info/readme/CONTRIBUTORS.rst
odoo/addons/account_move_line_landed_cost_info/readme/DESCRIPTION.rst
odoo/addons/account_move_line_landed_cost_info/readme/USAGE.rst
odoo/addons/account_move_line_landed_cost_info/static/description/icon.png
odoo/addons/account_move_line_landed_cost_info/static/description/index.html
odoo/addons/account_move_line_landed_cost_info/tests/__init__.py
odoo/addons/account_move_line_landed_cost_info/tests/test_account_move_line_landed_cost_info.py
odoo/addons/account_move_line_landed_cost_info/views/account_move_view.xml
odoo_addon_account_move_line_landed_cost_info-16.0.1.0.0.5.dist-info/METADATA
odoo_addon_account_move_line_landed_cost_info-16.0.1.0.0.5.dist-info/WHEEL
odoo_addon_account_move_line_landed_cost_info-16.0.1.0.0.5.dist-info/top_level.txt
odoo_addon_account_move_line_landed_cost_info-16.0.1.0.0.5.dist-info/RECORD
